kwiklib/__init__.py
kwiklib/dataio/__init__.py
kwiklib/dataio/chunks.py
kwiklib/dataio/experiment.py
kwiklib/dataio/klusterskwik.py
kwiklib/dataio/klustersloader.py
kwiklib/dataio/kwik.py
kwiklib/dataio/kwikloader.py
kwiklib/dataio/loader.py
kwiklib/dataio/probe.py
kwiklib/dataio/raw.py
kwiklib/dataio/selection.py
kwiklib/dataio/spikecache.py
kwiklib/dataio/tools.py
kwiklib/dataio/utils.py
kwiklib/dataio/tests/__init__.py
kwiklib/dataio/tests/mock.py
kwiklib/dataio/tests/mock_data.py
kwiklib/dataio/tests/test_chunks.py
kwiklib/dataio/tests/test_experiment.py
kwiklib/dataio/tests/test_klusterskwik.py
kwiklib/dataio/tests/test_klustersloader.py
kwiklib/dataio/tests/test_kwik.py
kwiklib/dataio/tests/test_kwikloader.py
kwiklib/dataio/tests/test_probe.py
kwiklib/dataio/tests/test_raw.py
kwiklib/dataio/tests/test_selection.py
kwiklib/dataio/tests/test_spikecache.py
kwiklib/dataio/tests/test_tools.py
kwiklib/dataio/tests/test_utils.py
kwiklib/scripts/__init__.py
kwiklib/scripts/runkwikkonvert.py
kwiklib/utils/__init__.py
kwiklib/utils/colors.py
kwiklib/utils/globalpaths.py
kwiklib/utils/logger.py
kwiklib/utils/params.py
kwiklib/utils/params_default.py
kwiklib/utils/persistence.py
kwiklib/utils/preferences_default.py
kwiklib/utils/probe.py
kwiklib/utils/pydict.py
kwiklib/utils/settings.py
kwiklib/utils/six.py
kwiklib/utils/testing.py
kwiklib/utils/userpref.py
kwiklib/utils/wrap.py
kwiklib/utils/tests/__init__.py
kwiklib/utils/tests/test_logger.py
kwiklib/utils/tests/test_params.py
kwiklib/utils/tests/test_probe.py
kwiklib/utils/tests/test_pydict.py
kwiklib/utils/tests/test_wrap.py
kwiklib-0.3.7.dist-info/DESCRIPTION.rst
kwiklib-0.3.7.dist-info/METADATA
kwiklib-0.3.7.dist-info/RECORD
kwiklib-0.3.7.dist-info/WHEEL
kwiklib-0.3.7.dist-info/metadata.json
kwiklib-0.3.7.dist-info/top_level.txt
