Metadata-Version: 2.0
Name: kwiklib
Version: 0.3.7
Summary: Kwiklib (legacy)
Home-page: http://klusta-team.github.io
Author: KwikTeam
Author-email: rossant@github
License: LICENSE.txt
Platform: UNKNOWN
